{
    "$schema": "http://adaptivecards.io/schemas/adaptive-card.json",
    "type": "AdaptiveCard",
    "version": "1.0",
    "body": [
    {
        "type": "ColumnSet",
        "columns": [
        {
            "type": "Column",
            "width": "5",
            "items": [
            {
                "type": "TextBlock",
                "text": "NAME OF PERSON",
                "size": "large",
                "horizontalAlignment": "Center",
                "weight": "Bolder"
            },
            {
                "type": "Image",
                "url": "High five profile icon here!",
                "size": "large",
                "horizontalAlignment": "Center",
                "style": "person"
            },
            {
                "type": "TextBlock",
                "text": "🎉",
                "horizontalAlignment": "Center",
                "size": "ExtraLarge"
            }
            ]
        }
        ]
    }
    ],
    "backgroundImage": {
    "url": "https://github.com/gabrielramp/high-five-bot/blob/f70792944fd5b96585c041ec18adfd53a74722d2/resources/highfivebackground.png?raw=true",
    "fillMode": "RepeatHorizontally"
    }
}
  